data_laundry/__init__.py
data_laundry-0.1.dist-info/LICENSE
data_laundry-0.1.dist-info/METADATA
data_laundry-0.1.dist-info/WHEEL
data_laundry-0.1.dist-info/top_level.txt
data_laundry-0.1.dist-info/RECORD
