Metadata-Version: 2.2
Name: data_laundry
Version: 0.1
Summary: A small python package to clean dirty data
Author-email: AamodJ <aamodj23@gmail.com>
Project-URL: Homepage, https://github.com/AamodJ/data_laundry
Project-URL: Issues, https://github.com/AamodJ/data_laundry/issues
Classifier: Programming Language :: Python :: 3
Classifier: Operating System :: OS Independent
Requires-Python: >=3.8
License-File: LICENSE
